<?xml version='1.0' encoding='utf-8'?>
<RDF:RDF xmlns:NS2="http://www.cellml.org/metadata/graphs/1.0#" xmlns:NS1="http://www.cellml.org/tools/pcenv/" xmlns:NC="http://home.netscape.com/NC-rdf#" xmlns:RDF="http://www.w3.org/1999/02/22-rdf-syntax-ns#">
  <RDF:Description RDF:about="http://www.cellml.org/tools/pcenv/modlayoutsplit" NS1:splitterState_collapsedBefore="true" NS1:splitterState_prevWidth="196" NS1:splitterState_nextWidth="1068"/>
  <RDF:Description RDF:about="rdf:#$orYgC3">
    <NS2:variable RDF:resource="luo_rudy_1991.cellml#plateau_potassium_current_i_Kp"/>
  </RDF:Description>
  <RDF:Description RDF:about="rdf:#$8rYgC3">
    <RDF:first RDF:resource="rdf:#$9rYgC3"/>
  </RDF:Description>
  <RDF:Description RDF:about="http://www.cellml.org/tools/pcenv/splitter/intergraph1" NS1:splitterState_prevHeight="235" NS1:splitterState_nextHeight="266"/>
  <RDF:Description RDF:about="rdf:#$6rYgC3">
    <RDF:first RDF:resource="http://www.w3.org/1999/02/22-rdf-syntax-ns#nil"/>
  </RDF:Description>
  <RDF:Description RDF:about="rdf:#$jrYgC3">
    <NS2:variable RDF:resource="luo_rudy_1991.cellml#environment_time"/>
  </RDF:Description>
  <RDF:Description RDF:about="rdf:#$5rYgC3">
    <RDF:first RDF:resource="rdf:#$FfYgC3"/>
    <RDF:rest RDF:resource="rdf:#$7rYgC3"/>
  </RDF:Description>
  <RDF:Description RDF:about="http://www.cellml.org/tools/pcenv/splitter/intergraph2" NS1:splitterState_prevHeight="266" NS1:splitterState_nextHeight="355"/>
  <RDF:Description RDF:about="rdf:#$erYgC3" NS2:colour="#ffff00">
    <NS2:type RDF:resource="http://www.cellml.org/metadata/graphs/1.0#line"/>
    <NS2:x-variable RDF:resource="rdf:#$frYgC3"/>
    <NS2:y-variable RDF:resource="rdf:#$grYgC3"/>
  </RDF:Description>
  <RDF:Description RDF:about="http://www.cellml.org/tools/pcenv/splitter/graph_sel_graph2">
    <NS1:activegraph RDF:resource="rdf:#$GfYgC3"/>
  </RDF:Description>
  <RDF:Description RDF:about="rdf:#$hrYgC3">
    <RDF:first RDF:resource="rdf:#$irYgC3"/>
    <RDF:rest RDF:resource="rdf:#$lrYgC3"/>
  </RDF:Description>
  <RDF:Description RDF:about="http://www.cellml.org/tools/pcenv/splitter/graph_key_graph1" NS1:splitterState_collapsedAfter="true" NS1:splitterState_prevHeight="221" NS1:splitterState_nextHeight="0"/>
  <RDF:Description RDF:about="rdf:#$GfYgC3" NS1:graphname="Channel Currents (microA_per_cm2)">
    <NS2:traces RDF:resource="rdf:#$8rYgC3"/>
  </RDF:Description>
  <RDF:Description RDF:about="rdf:#$vrYgC3">
    <NS2:variable RDF:resource="luo_rudy_1991.cellml#environment_time"/>
  </RDF:Description>
  <RDF:Description RDF:about="rdf:#$xrYgC3">
    <RDF:first RDF:resource="rdf:#$HfYgC3"/>
    <RDF:rest RDF:resource="http://www.w3.org/1999/02/22-rdf-syntax-ns#nil"/>
  </RDF:Description>
  <RDF:Description RDF:about="http://www.cellml.org/tools/pcenv/splitter/graph_key_graph3" NS1:splitterState_collapsedAfter="true" NS1:splitterState_nextHeight="0"/>
  <RDF:Seq RDF:about="http://www.cellml.org/tools/pcenv/loadedModels">
    <RDF:li RDF:resource="luo_rudy_1991.cellml"/>
  </RDF:Seq>
  <RDF:Description RDF:about="rdf:#$crYgC3">
    <NS2:variable RDF:resource="luo_rudy_1991.cellml#fast_sodium_current_i_Na"/>
  </RDF:Description>
  <RDF:Description RDF:about="http://www.cellml.org/tools/pcenv/splitter/graph_key_graph2" NS1:splitterState_collapsedAfter="true" NS1:splitterState_prevHeight="250" NS1:splitterState_nextHeight="0"/>
  <RDF:Description RDF:about="rdf:#$nrYgC3">
    <NS2:variable RDF:resource="luo_rudy_1991.cellml#environment_time"/>
  </RDF:Description>
  <RDF:Description RDF:about="rdf:#$7rYgC3">
    <RDF:first RDF:resource="rdf:#$GfYgC3"/>
    <RDF:rest RDF:resource="rdf:#$xrYgC3"/>
  </RDF:Description>
  <RDF:Description RDF:about="rdf:#$urYgC3" NS2:colour="#33ffff">
    <NS2:type RDF:resource="http://www.cellml.org/metadata/graphs/1.0#line"/>
    <NS2:x-variable RDF:resource="rdf:#$vrYgC3"/>
    <NS2:y-variable RDF:resource="rdf:#$wrYgC3"/>
  </RDF:Description>
  <RDF:Description RDF:about="rdf:#$CrYgC3">
    <NS2:variable RDF:resource="luo_rudy_1991.cellml#membrane_V"/>
  </RDF:Description>
  <RDF:Description RDF:about="rdf:#$irYgC3" NS2:colour="#ff0000">
    <NS2:type RDF:resource="http://www.cellml.org/metadata/graphs/1.0#line"/>
    <NS2:x-variable RDF:resource="rdf:#$jrYgC3"/>
    <NS2:y-variable RDF:resource="rdf:#$krYgC3"/>
  </RDF:Description>
  <RDF:Description RDF:about="rdf:#$yrYgC3">
    <RDF:first RDF:resource="rdf:#$zrYgC3"/>
  </RDF:Description>
  <RDF:Description RDF:about="rdf:#$grYgC3">
    <NS2:variable RDF:resource="luo_rudy_1991.cellml#slow_inward_current_i_si"/>
  </RDF:Description>
  <RDF:Description RDF:about="rdf:#$krYgC3">
    <NS2:variable RDF:resource="luo_rudy_1991.cellml#time_dependent_potassium_current_i_K"/>
  </RDF:Description>
  <RDF:Description RDF:about="rdf:#$lrYgC3">
    <RDF:first RDF:resource="rdf:#$mrYgC3"/>
    <RDF:rest RDF:resource="rdf:#$prYgC3"/>
  </RDF:Description>
  <RDF:Description RDF:about="rdf:#$brYgC3">
    <NS2:variable RDF:resource="luo_rudy_1991.cellml#environment_time"/>
  </RDF:Description>
  <RDF:Description RDF:about="rdf:#$prYgC3">
    <RDF:first RDF:resource="rdf:#$qrYgC3"/>
    <RDF:rest RDF:resource="rdf:#$trYgC3"/>
  </RDF:Description>
  <RDF:Description RDF:about="rdf:#$zrYgC3">
    <RDF:first RDF:resource="rdf:#$ArYgC3"/>
    <RDF:rest RDF:resource="http://www.w3.org/1999/02/22-rdf-syntax-ns#nil"/>
  </RDF:Description>
  <RDF:Description RDF:about="rdf:#$arYgC3" NS2:colour="#33ff33">
    <NS2:type RDF:resource="http://www.cellml.org/metadata/graphs/1.0#line"/>
    <NS2:x-variable RDF:resource="rdf:#$brYgC3"/>
    <NS2:y-variable RDF:resource="rdf:#$crYgC3"/>
  </RDF:Description>
  <RDF:Description RDF:about="rdf:#$BrYgC3">
    <NS2:variable RDF:resource="luo_rudy_1991.cellml#environment_time"/>
  </RDF:Description>
  <RDF:Seq RDF:about="rdf:#$4rYgC3">
  </RDF:Seq>
  <RDF:Description RDF:about="rdf:#$wrYgC3">
    <NS2:variable RDF:resource="luo_rudy_1991.cellml#time_independent_potassium_current_i_K1"/>
  </RDF:Description>
  <RDF:Description RDF:about="rdf:#$drYgC3">
    <RDF:first RDF:resource="rdf:#$erYgC3"/>
    <RDF:rest RDF:resource="rdf:#$hrYgC3"/>
  </RDF:Description>
  <RDF:Description RDF:about="rdf:#$ArYgC3" NS2:colour="#ff0000">
    <NS2:type RDF:resource="http://www.cellml.org/metadata/graphs/1.0#line"/>
    <NS2:x-variable RDF:resource="rdf:#$BrYgC3"/>
    <NS2:y-variable RDF:resource="rdf:#$CrYgC3"/>
  </RDF:Description>
  <RDF:Description RDF:about="rdf:#$9rYgC3">
    <RDF:first RDF:resource="rdf:#$arYgC3"/>
    <RDF:rest RDF:resource="rdf:#$drYgC3"/>
  </RDF:Description>
  <RDF:Description RDF:about="rdf:#$FfYgC3" NS1:graphname="Cell Diagram: click on channel to toggle display of graph trace above" NS1:externalurl="luo_rudy_1991.xul">
    <NS2:traces RDF:resource="rdf:#$6rYgC3"/>
  </RDF:Description>
  <RDF:Description RDF:about="http://www.cellml.org/tools/pcenv/splitter/graph_sel_graph3">
    <NS1:activegraph RDF:resource="rdf:#$FfYgC3"/>
  </RDF:Description>
  <RDF:Description RDF:about="rdf:#$trYgC3">
    <RDF:first RDF:resource="rdf:#$urYgC3"/>
    <RDF:rest RDF:resource="http://www.w3.org/1999/02/22-rdf-syntax-ns#nil"/>
  </RDF:Description>
  <RDF:Description RDF:about="http://www.cellml.org/tools/pcenv/displayGraphs">
    <RDF:first RDF:resource="rdf:#$5rYgC3"/>
  </RDF:Description>
  <RDF:Description RDF:about="http://www.cellml.org/tools/pcenv/splitter/graphedit" NS1:splitterState_prevWidth="453" NS1:splitterState_nextWidth="608"/>
  <RDF:Description RDF:about="rdf:#$rrYgC3">
    <NS2:variable RDF:resource="luo_rudy_1991.cellml#environment_time"/>
  </RDF:Description>
  <RDF:Description RDF:about="rdf:#$qrYgC3" NS2:colour="#ffffff">
    <NS2:type RDF:resource="http://www.cellml.org/metadata/graphs/1.0#line"/>
    <NS2:x-variable RDF:resource="rdf:#$rrYgC3"/>
    <NS2:y-variable RDF:resource="rdf:#$srYgC3"/>
  </RDF:Description>
  <RDF:Description RDF:about="luo_rudy_1991.cellml" NS1:modelname="luo_rudy_1991" NS1:modelfrozen="true">
    <NS1:derivedmodels RDF:resource="rdf:#$4rYgC3"/>
  </RDF:Description>
  <RDF:Description RDF:about="rdf:#$HfYgC3" NS1:graphname="Membrane Potential (mV)">
    <NS2:traces RDF:resource="rdf:#$yrYgC3"/>
  </RDF:Description>
  <RDF:Description RDF:about="rdf:#$mrYgC3" NS2:colour="#3366ff">
    <NS2:type RDF:resource="http://www.cellml.org/metadata/graphs/1.0#line"/>
    <NS2:x-variable RDF:resource="rdf:#$nrYgC3"/>
    <NS2:y-variable RDF:resource="rdf:#$orYgC3"/>
  </RDF:Description>
  <RDF:Description RDF:about="http://www.cellml.org/tools/pcenv/splitter/graph_sel_graph1">
    <NS1:activegraph RDF:resource="rdf:#$HfYgC3"/>
  </RDF:Description>
  <RDF:Description RDF:about="rdf:#$frYgC3">
    <NS2:variable RDF:resource="luo_rudy_1991.cellml#environment_time"/>
  </RDF:Description>
  <RDF:Description RDF:about="rdf:#$srYgC3">
    <NS2:variable RDF:resource="luo_rudy_1991.cellml#background_current_i_b"/>
  </RDF:Description>
</RDF:RDF>